[{"label":"bug","count":3618},{"label":"enhancement","count":2432},{"label":"type-bug","count":1781},{"label":"Sev2-normal","count":929},{"label":"status","count":584},{"label":"INVALID-ISSUE-TEMPLATE","count":508},{"label":"good first issue","count":485},{"label":"content \ud83d\udd8b\ufe0f","count":465},{"label":"stale","count":425},{"label":"C-enhancement","count":406},{"label":"translation \ud83c\udf0d","count":406},{"label":"documentation","count":394},{"label":"blocklist removal","count":388},{"label":"team-confirmations","count":383},{"label":"help wanted","count":377},{"label":"2 (Med Risk)","count":371},{"label":"unsatisfactory","count":345},{"label":"s-draft","count":323},{"label":"reject","count":317},{"label":"Payment Status: Requested","count":314},{"label":"Stellar Wave","count":299},{"label":"Sev1-high","count":298},{"label":"c-update","count":295},{"label":"feature","count":278},{"label":"T-bug","count":275},{"label":"needs-triage","count":270},{"label":"Status: Triage","count":265},{"label":"Sev3-low","count":262},{"label":"C-bug","count":257},{"label":"3 (High Risk)","count":256},{"label":"external-contributor","count":248},{"label":"team-assets","count":247},{"label":"release-blocker","count":246},{"label":"blocklist addition","count":245},{"label":"safe-tx-service-zk-sync-era-mainnet","count":244},{"label":"QA (Quality Assurance)","count":239},{"label":"abandoned","count":231},{"label":"testing","count":223},{"label":"Non-Reward","count":208},{"label":"e-consensus","count":202},{"label":"auto-closed","count":199},{"label":"Status: Stale","count":199},{"label":"frontend","count":196},{"label":"team-core-extension-ux","count":195},{"label":"quality-gate","count":195},{"label":"satisfactory","count":192},{"label":"a-review","count":192},{"label":"t-core","count":189},{"label":"ready-for-merge","count":186},{"label":"type: bug","count":185}]